Metadata-Version: 2.1
Name: illustration2vec
Version: 0.1.0
Summary: A simple deep learning library for estimating a set of tags and extracting semantic feature vectors from given illustrations.
Home-page: https://github.com/rezoo/illustration2vec/
Author: rezoo
Author-email: rezoolab@gmail.com
Maintainer: Rachmadani Haryono
Maintainer-email: foreturiga@gmail.com
License: MIT License
Project-URL: Bug Tracker, https://github.com/rezoo/illustration2vec/issues
Keywords: machine learning tag image illustration
Platform: UNKNOWN
Provides-Extra: dev
